README.rst
setup.py
gmpy_cffi/__init__.py
gmpy_cffi/cache.py
gmpy_cffi/convert.py
gmpy_cffi/interface.py
gmpy_cffi/mpc.py
gmpy_cffi/mpfr.py
gmpy_cffi/mpq.py
gmpy_cffi/mpz.py
gmpy_cffi/ntheory.py
gmpy_cffi/special_functions.py
gmpy_cffi/version.py
gmpy_cffi.egg-info/PKG-INFO
gmpy_cffi.egg-info/SOURCES.txt
gmpy_cffi.egg-info/dependency_links.txt
gmpy_cffi.egg-info/not-zip-safe
gmpy_cffi.egg-info/top_level.txt
gmpy_cffi/__pycache__/_cffi__x1666db10xdc48b72e.c
gmpy_cffi/__pycache__/_cffi__x6f0caaex9cbb9358.c