Metadata-Version: 1.1
Name: gmpy-cffi
Version: 0.1
Summary: GMP CFFI wrapper
Home-page: https://github.com/sn6uv/gmpy_cffi
Author: Angus Griffith
Author-email: 16sn6uv@gmail.com
License: 3-clause BSD
Download-URL: https://github.com/sn6uv/gmpy_cffi/tarball/0.1
Keywords: PyPy,gmp
Platform: UNKNOWN
Classifier: Development Status :: 2 - Pre-Alpha
Classifier: Intended Audience :: Developers
Classifier: Intended Audience :: Science/Research
Classifier: License :: OSI Approved :: BSD License
Classifier: Natural Language :: English
Classifier: Operating System :: MacOS :: MacOS X
Classifier: Operating System :: Microsoft :: Windows
Classifier: Operating System :: POSIX
Classifier: Programming Language :: Python :: 2
Classifier: Programming Language :: Python :: 3
Classifier: Programming Language :: Python :: Implementation :: CPython
Classifier: Programming Language :: Python :: Implementation :: PyPy
Classifier: Topic :: Scientific/Engineering :: Mathematics
Classifier: Topic :: Software Development :: Libraries :: Python Modules
